robutler/__init__.py
robutler/agents/__init__.py
robutler/agents/core/__init__.py
robutler/agents/core/base_agent.py
robutler/agents/core/handoffs.py
robutler/agents/handoffs/__init__.py
robutler/agents/interfaces/__init__.py
robutler/agents/lifecycle/__init__.py
robutler/agents/skills/__init__.py
robutler/agents/skills/base.py
robutler/agents/skills/core/__init__.py
robutler/agents/skills/core/guardrails/__init__.py
robutler/agents/skills/core/llm/__init__.py
robutler/agents/skills/core/llm/anthropic/__init__.py
robutler/agents/skills/core/llm/litellm/__init__.py
robutler/agents/skills/core/llm/litellm/skill.py
robutler/agents/skills/core/llm/openai/__init__.py
robutler/agents/skills/core/llm/xai/__init__.py
robutler/agents/skills/core/mcp/README.md
robutler/agents/skills/core/mcp/__init__.py
robutler/agents/skills/core/mcp/skill.py
robutler/agents/skills/core/memory/__init__.py
robutler/agents/skills/core/memory/long_term_memory/__init__.py
robutler/agents/skills/core/memory/long_term_memory/memory_skill.py
robutler/agents/skills/core/memory/short_term_memory/__init__.py
robutler/agents/skills/core/memory/short_term_memory/skill.py
robutler/agents/skills/core/memory/vector_memory/skill.py
robutler/agents/skills/core/planning/__init__.py
robutler/agents/skills/core/planning/planner.py
robutler/agents/skills/ecosystem/__init__.py
robutler/agents/skills/ecosystem/crewai/__init__.py
robutler/agents/skills/ecosystem/database/__init__.py
robutler/agents/skills/ecosystem/filesystem/__init__.py
robutler/agents/skills/ecosystem/google/__init__.py
robutler/agents/skills/ecosystem/google/calendar/__init__.py
robutler/agents/skills/ecosystem/google/calendar/skill.py
robutler/agents/skills/ecosystem/n8n/__init__.py
robutler/agents/skills/ecosystem/openai_agents/__init__.py
robutler/agents/skills/ecosystem/web/__init__.py
robutler/agents/skills/ecosystem/zapier/__init__.py
robutler/agents/skills/robutler/__init__.py
robutler/agents/skills/robutler/storage.py
robutler-0.2.0.dist-info/METADATA
robutler-0.2.0.dist-info/WHEEL
robutler-0.2.0.dist-info/entry_points.txt
robutler-0.2.0.dist-info/licenses/LICENSE
robutler-0.2.0.dist-info/RECORD
