Metadata-Version: 2.4
Name: robutler
Version: 0.2.0
Summary: Web AI Agents SDK
Author: Awesome Opensource Contributors and Robutler Team
License: TBD
License-File: LICENSE
Requires-Python: >=3.10
Requires-Dist: colorama>=0.4.6
Requires-Dist: fastapi>=0.100.0
Requires-Dist: fastmcp>=2.3.0
Requires-Dist: httpx>=0.24.0
Requires-Dist: litellm>=1.0.0
Requires-Dist: pillow>=10.0.0
Requires-Dist: pydantic-settings>=2.0.0
Requires-Dist: pydantic>=2.7.0
Requires-Dist: python-dotenv>=1.0.0
Requires-Dist: tiktoken>=0.5.0
Requires-Dist: uvicorn>=0.23.0
Provides-Extra: dev
Requires-Dist: black>=23.0.0; extra == 'dev'
Requires-Dist: mypy>=1.0.0; extra == 'dev'
Requires-Dist: pytest-asyncio>=0.21.0; extra == 'dev'
Requires-Dist: pytest>=7.0.0; extra == 'dev'
Requires-Dist: ruff>=0.0.270; extra == 'dev'
Provides-Extra: examples
Requires-Dist: openai-agents>=0.0.16; extra == 'examples'
